vivarium_cluster_tools/__about__.py
vivarium_cluster_tools/__init__.py
vivarium_cluster_tools/_version.py
vivarium_cluster_tools/cli_tools.py
vivarium_cluster_tools/logs.py
vivarium_cluster_tools/utilities.py
vivarium_cluster_tools/psimulate/__init__.py
vivarium_cluster_tools/psimulate/branches.py
vivarium_cluster_tools/psimulate/cli.py
vivarium_cluster_tools/psimulate/environment.py
vivarium_cluster_tools/psimulate/jobs.py
vivarium_cluster_tools/psimulate/model_specification.py
vivarium_cluster_tools/psimulate/paths.py
vivarium_cluster_tools/psimulate/performance_logger.py
vivarium_cluster_tools/psimulate/pip_env.py
vivarium_cluster_tools/psimulate/runner.py
vivarium_cluster_tools/psimulate/cluster/__init__.py
vivarium_cluster_tools/psimulate/cluster/cli_options.py
vivarium_cluster_tools/psimulate/cluster/interface.py
vivarium_cluster_tools/psimulate/redis_dbs/__init__.py
vivarium_cluster_tools/psimulate/redis_dbs/cli_options.py
vivarium_cluster_tools/psimulate/redis_dbs/launcher.py
vivarium_cluster_tools/psimulate/redis_dbs/registry.py
vivarium_cluster_tools/psimulate/results/__init__.py
vivarium_cluster_tools/psimulate/results/cli_options.py
vivarium_cluster_tools/psimulate/results/processing.py
vivarium_cluster_tools/psimulate/worker/__init__.py
vivarium_cluster_tools/psimulate/worker/core.py
vivarium_cluster_tools/psimulate/worker/load_test_work_horse.py
vivarium_cluster_tools/psimulate/worker/vivarium_work_horse.py
vivarium_cluster_tools/vipin/__init__.py
vivarium_cluster_tools/vipin/cli.py
vivarium_cluster_tools/vipin/perf_counters.py
vivarium_cluster_tools/vipin/perf_report.py
vivarium_cluster_tools-2.1.26.dist-info/licenses/LICENSE
vivarium_cluster_tools-2.1.26.dist-info/METADATA
vivarium_cluster_tools-2.1.26.dist-info/WHEEL
vivarium_cluster_tools-2.1.26.dist-info/entry_points.txt
vivarium_cluster_tools-2.1.26.dist-info/top_level.txt
vivarium_cluster_tools-2.1.26.dist-info/RECORD
