Metadata-Version: 2.4
Name: vivarium_cluster_tools
Version: 2.1.26
Summary: A set of tools for running simulation using vivarium on cluster.
Home-page: https://github.com/ihmeuw/vivarium_cluster_tools
Author: The vivarium developers
Author-email: vivarium.dev@gmail.com
License-File: LICENSE
Requires-Dist: vivarium_dependencies[click,loguru,numpy_lt_2,pandas,pyarrow,pyyaml,requests,tables]
Requires-Dist: vivarium_build_utils<3.0.0,>=2.0.1
Requires-Dist: drmaa
Requires-Dist: dill
Requires-Dist: redis
Requires-Dist: rq
Requires-Dist: vivarium>=3.0.0
Requires-Dist: psutil
Requires-Dist: layered_config_tree
Provides-Extra: docs
Requires-Dist: vivarium_dependencies[ipython,matplotlib,sphinx,sphinx-click]; extra == "docs"
Provides-Extra: interactive
Requires-Dist: vivarium_dependencies[interactive]; extra == "interactive"
Provides-Extra: test
Requires-Dist: vivarium_dependencies[pytest]; extra == "test"
Provides-Extra: dev
Requires-Dist: vivarium_dependencies[ipython,matplotlib,sphinx,sphinx-click]; extra == "dev"
Requires-Dist: vivarium_dependencies[interactive]; extra == "dev"
Requires-Dist: vivarium_dependencies[pytest]; extra == "dev"
Requires-Dist: vivarium_dependencies[lint]; extra == "dev"
Requires-Dist: types-setuptools; extra == "dev"
Requires-Dist: types-psutil; extra == "dev"
Dynamic: author
Dynamic: author-email
Dynamic: description
Dynamic: home-page
Dynamic: license-file
Dynamic: provides-extra
Dynamic: requires-dist
Dynamic: summary
